egybest/__init__.py
egycli/__init__.py
egycli/__main__.py
egycli-0.0.3.dist-info/LICENSE
egycli-0.0.3.dist-info/METADATA
egycli-0.0.3.dist-info/WHEEL
egycli-0.0.3.dist-info/entry_points.txt
egycli-0.0.3.dist-info/top_level.txt
egycli-0.0.3.dist-info/RECORD
