Metadata-Version: 2.1
Name: egycli
Version: 0.0.3
Summary: Downloading movies and tv shows thorugh egybest
Author: Cytolytic (Aktham Mostafa)
Author-email: cytolyticdev@gmail.com
License: UNKNOWN
Keywords: egybest,python,movies,download
Platform: UNKNOWN
License-File: LICENSE
Requires-Dist: rich
Requires-Dist: requests
Requires-Dist: beautifulsoup4
Requires-Dist: Js2Py
Requires-Dist: simple-term-menu
